dash_vizlink_components/Breadcrumbs.py
dash_vizlink_components/__init__.py
dash_vizlink_components/_imports_.py
dash_vizlink_components/dash_vizlink_components.min.js
dash_vizlink_components/dash_vizlink_components.min.js.map
dash_vizlink_components/metadata.json
dash_vizlink_components/package-info.json
dash_vizlink_components-0.0.1.dist-info/LICENSE
dash_vizlink_components-0.0.1.dist-info/METADATA
dash_vizlink_components-0.0.1.dist-info/WHEEL
dash_vizlink_components-0.0.1.dist-info/top_level.txt
dash_vizlink_components-0.0.1.dist-info/RECORD
